autostore/__init__.py
autostore/calcn/__init__.py
autostore/calcn/core.py
autostore/calcn/registry.py
autostore/calcn/util.py
autostore/database.py
autostore/models/__init__.py
autostore/models/calculation.py
autostore/models/data.py
autostore/models/geometry.py
autostore/qc/__init__.py
autostore/qc/structure.py
autostore/read.py
autostore/types/__init__.py
autostore/types/sqlalchemy.py
autostore/write.py
automech_autostore-0.0.3.dist-info/WHEEL
automech_autostore-0.0.3.dist-info/METADATA
automech_autostore-0.0.3.dist-info/RECORD
