Metadata-Version: 2.3
Name: automech-autostore
Version: 0.0.3
Author: Andreas V. Copan
Author-email: Andreas V. Copan <avcopan@uga.edu>
Requires-Dist: automol==0.0.5
Requires-Dist: pint>=0.25.2
Requires-Dist: qcio>=0.16.2
Requires-Dist: sqlmodel>=0.0.31
Requires-Python: >=3.12
